lhapdf_management/__init__.py
lhapdf_management/configuration.py
lhapdf_management/management.py
lhapdf_management/net_utilities.py
lhapdf_management/pdfsets.py
lhapdf_management/scripts/__init__.py
lhapdf_management/scripts/lhapdf_script.py
lhapdf_management-0.6.dist-info/licenses/LICENSE
lhapdf_management-0.6.dist-info/METADATA
lhapdf_management-0.6.dist-info/WHEEL
lhapdf_management-0.6.dist-info/entry_points.txt
lhapdf_management-0.6.dist-info/top_level.txt
lhapdf_management-0.6.dist-info/RECORD
