Metadata-Version: 2.4
Name: lhapdf_management
Version: 0.6
Summary: python-only lhapdf management
Author-email: Juan Cruz-Martinez <juacrumar@lairen.eu>
License: GPLv3
Project-URL: repository, https://github.com/scarlehoff/lhapdf_management
Classifier: Operating System :: Unix
Classifier: Programming Language :: Python
Classifier: Programming Language :: Python :: 3
Classifier: Topic :: Scientific/Engineering
Classifier: Topic :: Scientific/Engineering :: Physics
Requires-Python: >=3.6
License-File: LICENSE
Requires-Dist: pyyaml
Requires-Dist: numpy
Provides-Extra: fancy
Requires-Dist: tqdm; extra == "fancy"
Provides-Extra: tests
Requires-Dist: pytest; extra == "tests"
Requires-Dist: pytest-order; extra == "tests"
Dynamic: license-file
